pkginfo/__init__.py
pkginfo/__init__.pyi
pkginfo/bdist.py
pkginfo/bdist.pyi
pkginfo/commandline.py
pkginfo/commandline.pyi
pkginfo/develop.py
pkginfo/develop.pyi
pkginfo/distribution.py
pkginfo/distribution.pyi
pkginfo/index.py
pkginfo/index.pyi
pkginfo/installed.py
pkginfo/installed.pyi
pkginfo/py.typed
pkginfo/sdist.py
pkginfo/sdist.pyi
pkginfo/utils.py
pkginfo/utils.pyi
pkginfo/wheel.py
pkginfo/wheel.pyi
pkginfo/tests/__init__.py
pkginfo/tests/conftest.py
pkginfo/tests/test_bdist.py
pkginfo/tests/test_commandline.py
pkginfo/tests/test_develop.py
pkginfo/tests/test_distribution.py
pkginfo/tests/test_index.py
pkginfo/tests/test_installed.py
pkginfo/tests/test_sdist.py
pkginfo/tests/test_utils.py
pkginfo/tests/test_wheel.py
pkginfo-1.12.1.dist-info/LICENSE.txt
pkginfo-1.12.1.dist-info/METADATA
pkginfo-1.12.1.dist-info/WHEEL
pkginfo-1.12.1.dist-info/entry_points.txt
pkginfo-1.12.1.dist-info/top_level.txt
pkginfo-1.12.1.dist-info/RECORD
